MANIFEST.in
pavement.py
paver-minilib.zip
setup.py
btree.egg-info/PKG-INFO
btree.egg-info/SOURCES.txt
btree.egg-info/dependency_links.txt
btree.egg-info/top_level.txt
src/btree_common.c
src/btree_common.h
src/btreemodule.c
src/offsetstring.h
src/sorted_btree.c
src/sorted_btree.h