Metadata-Version: 1.1
Name: btree
Version: 0.2.0
Summary: BTree implementation as a C python extension
Home-page: http://github.com/teepark/btree
Author: Travis J Parker
Author-email: travis.parker@gmail.com
License: BSD
Platform: UNKNOWN
Classifier: Development Status :: 3 - Alpha
Classifier: Intended Audience :: Developers
Classifier: License :: OSI Approved :: BSD License
Classifier: Natural Language :: English
Classifier: Programming Language :: C
